{
    "0": {
        "key_frame": 25,
        "detail_frames": []
    },
    "1": {
        "key_frame": 30,
        "detail_frames": []
    },
    "2": {
        "key_frame": 35,
        "detail_frames": []
    },
    "3": {
        "key_frame": 40,
        "detail_frames": []
    },
    "4": {
        "key_frame": 45,
        "detail_frames": []
    },
    "5": {
        "key_frame": 50,
        "detail_frames": []
    },
    "6": {
        "key_frame": 55,
        "detail_frames": []
    },
    "7": {
        "key_frame": 60,
        "detail_frames": []
    },
    "8": {
        "key_frame": 75,
        "detail_frames": [
            115
        ]
    },
    "9": {
        "key_frame": 140,
        "detail_frames": []
    }
}